laiagenlib/__init__.py
laiagenlib/Application/__init__.py
laiagenlib/Application/AccessRights/CheckAccessRightsOfFields.py
laiagenlib/Application/AccessRights/CheckAccessRightsOfUser.py
laiagenlib/Application/AccessRights/CreateAccessRights.py
laiagenlib/Application/AccessRights/GetAllowedFields.py
laiagenlib/Application/AccessRights/UpdateAccessRights.py
laiagenlib/Application/AccessRights/__init__.py
laiagenlib/Application/LaiaBaseModel/AggregateLaiaBaseModel.py
laiagenlib/Application/LaiaBaseModel/CreateLaiaBaseModel.py
laiagenlib/Application/LaiaBaseModel/DeleteLaiaBaseModel.py
laiagenlib/Application/LaiaBaseModel/ReadLaiaBaseModel.py
laiagenlib/Application/LaiaBaseModel/SearchLaiaBaseModel.py
laiagenlib/Application/LaiaBaseModel/UpdateLaiaBaseModel.py
laiagenlib/Application/LaiaBaseModel/__init__.py
laiagenlib/Application/LaiaUser/CreateLaiaUser.py
laiagenlib/Application/LaiaUser/CreateRole.py
laiagenlib/Application/LaiaUser/JWTToken.py
laiagenlib/Application/LaiaUser/LoginLaiaUser.py
laiagenlib/Application/LaiaUser/RegisterLaiaUser.py
laiagenlib/Application/LaiaUser/UpdateLaiaUser.py
laiagenlib/Application/LaiaUser/VerifyLaiaUser.py
laiagenlib/Application/LaiaUser/__init__.py
laiagenlib/Application/Openapi/CreateFlutterApp.py
laiagenlib/Application/Openapi/CreateRoutes.py
laiagenlib/Application/Openapi/__init__.py
laiagenlib/Application/Shared/__init__.py
laiagenlib/Application/Shared/Exception/__init__.py
laiagenlib/Application/Shared/Utils/CreateBaseFiles.py
laiagenlib/Application/Shared/Utils/CreateModelsFile.py
laiagenlib/Application/Shared/Utils/CreateRoutesFile.py
laiagenlib/Application/Shared/Utils/DownloadImage.py
laiagenlib/Application/Shared/Utils/ExtractClassInfo.py
laiagenlib/Application/Shared/Utils/Schemas.py
laiagenlib/Application/Shared/Utils/SendEmail.py
laiagenlib/Application/Shared/Utils/Slugify.py
laiagenlib/Application/Shared/Utils/UpdateFile.py
laiagenlib/Application/Shared/Utils/UserShard.py
laia_gen_lib-0.4.37.dist-info/METADATA
laia_gen_lib-0.4.37.dist-info/WHEEL
laia_gen_lib-0.4.37.dist-info/top_level.txt
laia_gen_lib-0.4.37.dist-info/RECORD
