Metadata-Version: 2.4
Name: laia-gen-lib
Version: 0.4.37
Summary: An AI application generator engine
Author: Me
Requires-Dist: pymongo
Requires-Dist: pydantic==2.8.0
Requires-Dist: datamodel-code-generator==0.25.8
Requires-Dist: fastapi==0.111.0
Requires-Dist: bcrypt
Requires-Dist: asyncinit
Requires-Dist: pyjwt
Dynamic: author
Dynamic: requires-dist
Dynamic: summary
